py_hpl_logger-0.2.5.dist-info/METADATA
py_hpl_logger-0.2.5.dist-info/WHEEL
py_hpl_logger/__init__.py
py_hpl_logger/handler.py
py_hpl_logger/py_hpl_logger.cpython-314t-powerpc64le-linux-gnu.so
py_hpl_logger/py_hpl_logger.pyi
py_hpl_logger-0.2.5.dist-info/RECORD
