Metadata-Version: 2.4
Name: py_hpl_logger
Version: 0.2.5
Classifier: Programming Language :: Python :: 3.9
Classifier: Topic :: System :: Logging
Classifier: Programming Language :: Rust
Classifier: License :: OSI Approved :: MIT License
Classifier: Programming Language :: Python :: Implementation :: CPython
Classifier: Programming Language :: Python :: Implementation :: PyPy
Classifier: Framework :: AsyncIO
Classifier: Development Status :: 4 - Beta
Requires-Dist: pip>=21
Requires-Dist: pytest ; extra == 'tests'
Provides-Extra: tests
Summary: A high-performance, buffered, non-blocking logger for Python, implemented in Rust.
Keywords: logging,logger,elasticsearch,elastic,rust,performance,non-blocking,autoflush
Author-email: Pavel Nikitin <1@pashanikitin.ru>
License: MIT
Requires-Python: >=3.9
